fast_depends/__about__.py
fast_depends/__init__.py
fast_depends/_compat.py
fast_depends/core/__init__.py
fast_depends/core/builder.py
fast_depends/core/model.py
fast_depends/dependencies/__init__.py
fast_depends/dependencies/model.py
fast_depends/dependencies/provider.py
fast_depends/exceptions.py
fast_depends/library/__init__.py
fast_depends/library/model.py
fast_depends/library/serializer.py
fast_depends/msgspec/__init__.py
fast_depends/msgspec/serializer.py
fast_depends/py.typed
fast_depends/pydantic/__init__.py
fast_depends/pydantic/_compat.py
fast_depends/pydantic/schema.py
fast_depends/pydantic/serializer.py
fast_depends/use.py
fast_depends/utils.py
fast_depends-3.0.3.dist-info/licenses/LICENSE
fast_depends-3.0.3.dist-info/WHEEL
fast_depends-3.0.3.dist-info/METADATA
fast_depends-3.0.3.dist-info/RECORD
