Metadata-Version: 2.4
Name: fast-depends
Version: 3.0.3
Summary: FastDepends - extracted and cleared from HTTP domain logic FastAPI Dependency Injection System. Async and sync are both supported.
Keywords: fastapi,dependency injection
Author: Nikita Pastukhov
Author-email: Nikita Pastukhov <nikita@pastukhov-dev.com>
License-Expression: MIT
License-File: LICENSE
Classifier: Development Status :: 5 - Production/Stable
Classifier: License :: OSI Approved :: MIT License
Classifier: Programming Language :: Python
Classifier: Programming Language :: Python :: Implementation :: CPython
Classifier: Programming Language :: Python :: 3
Classifier: Programming Language :: Python :: 3 :: Only
Classifier: Programming Language :: Python :: 3.10
Classifier: Programming Language :: Python :: 3.11
Classifier: Programming Language :: Python :: 3.12
Classifier: Programming Language :: Python :: 3.13
Classifier: Programming Language :: Python :: 3.14
Classifier: Operating System :: OS Independent
Classifier: Topic :: Software Development :: Libraries :: Python Modules
Classifier: Topic :: Software Development :: Libraries
Classifier: Topic :: Software Development
Classifier: Typing :: Typed
Classifier: Intended Audience :: Developers
Classifier: Intended Audience :: Information Technology
Classifier: Framework :: Pydantic
Classifier: Framework :: Pydantic :: 1
Classifier: Framework :: Pydantic :: 2
Requires-Dist: anyio>=4.0.0,<5.0.0
Requires-Dist: typing-extensions!=4.12.1
Requires-Dist: msgspec ; extra == 'msgspec'
Requires-Dist: pydantic>=1.7.4,!=1.8,!=1.8.1,<3.0.0 ; extra == 'pydantic'
Requires-Python: >=3.10
Project-URL: Documentation, https://lancetnik.github.io/FastDepends/
Project-URL: Homepage, https://lancetnik.github.io/FastDepends/
Project-URL: Source, https://github.com/Lancetnik/FastDepends
Project-URL: Tracker, https://github.com/Lancetnik/FastDepends/issues
Provides-Extra: msgspec
Provides-Extra: pydantic
